{
	"credit": "Made with Blockbench",
	"parent": "block/block",
	"textures": {
		"particle": "primalmagic:block/marble_raw",
		"bottom": "primalmagic:block/marble_raw",
		"top": "block/enchanting_table_top",
		"side": "primalmagic:block/runescribing_altar_basic_side"
	},
	"elements": [
		{
			"from": [0, 0, 0],
			"to": [16, 12, 16],
			"faces": {
				"north": {"uv": [0, 4, 16, 16], "texture": "#side", "cullface": "north"},
				"east": {"uv": [0, 4, 16, 16], "texture": "#side", "cullface": "east"},
				"south": {"uv": [0, 4, 16, 16], "texture": "#side", "cullface": "south"},
				"west": {"uv": [0, 4, 16, 16], "texture": "#side", "cullface": "west"},
				"up": {"uv": [0, 0, 16, 16], "texture": "#top"},
				"down": {"uv": [0, 0, 16, 16], "texture": "#bottom", "cullface": "down"}
			}
		}
	]
}