{
    "variants": {
        "type=bottom,phase=full": { "model": "primalmagic:block/sunwood_slab_bottom_full" },
        "type=top,phase=full":    { "model": "primalmagic:block/sunwood_slab_top_full" },
        "type=double,phase=full": { "model": "primalmagic:block/sunwood_planks_full" },
        "type=bottom,phase=waxing": { "model": "primalmagic:block/sunwood_slab_bottom_waxing" },
        "type=top,phase=waxing":    { "model": "primalmagic:block/sunwood_slab_top_waxing" },
        "type=double,phase=waxing": { "model": "primalmagic:block/sunwood_planks_waxing" },
        "type=bottom,phase=waning": { "model": "primalmagic:block/sunwood_slab_bottom_waning" },
        "type=top,phase=waning":    { "model": "primalmagic:block/sunwood_slab_top_waning" },
        "type=double,phase=waning": { "model": "primalmagic:block/sunwood_planks_waning" },
        "type=bottom,phase=faded": { "model": "primalmagic:block/sunwood_slab_bottom_faded" },
        "type=top,phase=faded":    { "model": "primalmagic:block/sunwood_slab_top_faded" },
        "type=double,phase=faded": { "model": "primalmagic:block/sunwood_planks_faded" }
    }
}
