{
  "addenda": [],
  "discipline": "SCANS",
  "hidden": true,
  "icon": {
    "isItem": true,
    "location": "primalmagick:hallowood_sapling"
  },
  "key": "HALLOWOOD_TREES",
  "name": "research.primalmagick.hallowood_trees.title",
  "parents": [
    "UNLOCK_SCANS"
  ],
  "stages": [
    {
      "recipes": [
        "primalmagick:hallowood_wood",
        "primalmagick:stripped_hallowood_wood",
        "primalmagick:hallowood_planks",
        "primalmagick:hallowood_slab",
        "primalmagick:hallowood_stairs",
        "primalmagick:hallowood_pillar"
      ],
      "text": "research.primalmagick.hallowood_trees.text.stage.1"
    }
  ]
}