{
  "addenda": [],
  "discipline": "SCANS",
  "hidden": true,
  "icon": {
    "isItem": true,
    "location": "primalmagick:refined_salt"
  },
  "key": "ROCK_SALT",
  "name": "research.primalmagick.rock_salt.title",
  "parents": [
    "UNLOCK_SCANS"
  ],
  "stages": [
    {
      "recipes": [
        "primalmagick:refined_salt",
        "primalmagick:rock_salt_from_smelting",
        "primalmagick:salt_block",
        "primalmagick:refined_salt_from_salt_block",
        "primalmagick:salted_baked_potato",
        "primalmagick:salted_beetroot_soup",
        "primalmagick:salted_cooked_beef",
        "primalmagick:salted_cooked_chicken",
        "primalmagick:salted_cooked_cod",
        "primalmagick:salted_cooked_mutton",
        "primalmagick:salted_cooked_porkchop",
        "primalmagick:salted_cooked_rabbit",
        "primalmagick:salted_cooked_salmon",
        "primalmagick:salted_mushroom_stew",
        "primalmagick:salted_rabbit_stew"
      ],
      "text": "research.primalmagick.rock_salt.text.stage.1"
    }
  ]
}