{
  "addenda": [
    {
      "recipes": [
        "primalmagick:sunwood_staff_core_item"
      ],
      "required_research": [
        "STAVES"
      ],
      "text": "research.primalmagick.wand_core_sunwood.text.addenda.1"
    }
  ],
  "discipline": "MANAWEAVING",
  "icon": {
    "isItem": true,
    "location": "primalmagick:sunwood_wand_core_item"
  },
  "key": "WAND_CORE_SUNWOOD",
  "name": "research.primalmagick.wand_core_sunwood.title",
  "parents": [
    "EXPERT_MANAWEAVING",
    "WAND_CORE_OBSIDIAN"
  ],
  "stages": [
    {
      "required_item": [
        "primalmagick:sunwood_log"
      ],
      "required_knowledge": [
        "THEORY;1"
      ],
      "text": "research.primalmagick.wand_core_sunwood.text.stage.1"
    },
    {
      "attunements": {
        "sun": 2
      },
      "recipes": [
        "primalmagick:sunwood_wand_core_item"
      ],
      "text": "research.primalmagick.wand_core_sunwood.text.stage.2"
    }
  ]
}