{
  "key": "RUNE_CREATURE",
  "name": "primalmagick.research.rune_creature.title",
  "discipline": "RUNEWORKING",
  "icon": {
    "isItem": true,
    "location": "primalmagick:rune_creature"
  },
  "parents": [
    "EXPERT_RUNEWORKING"
  ],
  "stages": [
    {
      "text": "primalmagick.research.rune_creature.text.stage.1",
      "required_knowledge": [
        "THEORY;1"
      ]
    },
    {
      "text": "primalmagick.research.rune_creature.text.stage.2",
      "recipes": [
        "primalmagick:rune_creature"
      ]
    }
  ],
  "addenda": []
}