{
  "key": "WAND_CORE_MOONWOOD",
  "name": "primalmagick.research.wand_core_moonwood.title",
  "discipline": "MANAWEAVING",
  "icon": {
    "isItem": true,
    "location": "primalmagick:moonwood_wand_core_item"
  },
  "parents": [
    "EXPERT_MANAWEAVING",
    "WAND_CORE_OBSIDIAN"
  ],
  "stages": [
    {
      "text": "primalmagick.research.wand_core_moonwood.text.stage.1",
      "required_item": [
        "primalmagick:moonwood_log"
      ],
      "required_knowledge": [
        "THEORY;1"
      ]
    },
    {
      "text": "primalmagick.research.wand_core_moonwood.text.stage.2",
      "attunements": {
        "moon": 2
      },
      "recipes": [
        "primalmagick:moonwood_wand_core_item"
      ]
    }
  ],
  "addenda": [
    {
      "text": "primalmagick.research.wand_core_moonwood.text.addenda.1",
      "required_research": [
        "STAVES"
      ],
      "recipes": [
        "primalmagick:moonwood_staff_core_item"
      ]
    }
  ]
}