{
  "type": "primalmagick:ritual",
  "ingredients": [
    {
      "tag": "minecraft:wool_carpets"
    },
    {
      "item": "minecraft:saddle"
    },
    {
      "item": "minecraft:feather"
    },
    {
      "item": "primalmagick:mana_salts"
    },
    {
      "item": "primalmagick:essence_crystal_sky"
    },
    {
      "item": "primalmagick:essence_crystal_sky"
    },
    {
      "item": "primalmagick:rune_project"
    },
    {
      "item": "primalmagick:rune_item"
    },
    {
      "item": "primalmagick:rune_insight"
    }
  ],
  "instability": 6,
  "mana": {
    "sources": {
      "sky": 100
    }
  },
  "props": [
    {
      "block": "primalmagick:incense_brazier"
    },
    {
      "block": "primalmagick:incense_brazier"
    },
    {
      "block": "primalmagick:ritual_bell"
    },
    {
      "block": "primalmagick:ritual_lectern"
    }
  ],
  "research": "FLYING_CARPET",
  "result": {
    "Count": 1,
    "id": "primalmagick:flying_carpet"
  }
}